{
 "WKSH.tuning.title": "🔧 Atelier de Mod",
 "WKSH.tuning.warn.noItems": "{name} n'a aucune arme/armure avec des emplacements.",
 "WKSH.tuning.mode.intro": "Sur l'équipement de <b>{name}</b>, que veux-tu faire ?",
 "WKSH.tuning.mode.install": "<b>Poser un accessoire</b> : monte une pièce sur un emplacement (difficulté selon rareté).",
 "WKSH.tuning.mode.mod": "<b>Activer un mod</b> : améliore un accessoire déjà posé — la difficulté monte de 1 par mod déjà activé sur cet accessoire (règle du livre).",
 "WKSH.tuning.btn.install": "Poser un accessoire",
 "WKSH.tuning.btn.mod": "Activer un mod (accessoire posé)",
 "WKSH.tuning.install.title": "🔧 Réglage — pose d'un accessoire",
 "WKSH.tuning.lbl.item": "Objet à régler",
 "WKSH.tuning.lbl.att": "Accessoire",
 "WKSH.tuning.opt.item": "{name} — Emp. {used}/{total}",
 "WKSH.tuning.opt.att": "{name} (Emp.{hp}, {price}cr, R{rarity})",
 "WKSH.tuning.btn.installRoll": "Installer + lancer le test",
 "WKSH.tuning.btn.noRoll": "Noter sans test",
 "WKSH.tuning.sum.free": "<b>{name}</b> — emplacements libres : {free}",
 "WKSH.tuning.sum.att": "Accessoire : <b>{name}</b> — coûte <b>{hp}</b> emplacement(s), {price} cr, rareté {rarity}.",
 "WKSH.tuning.sum.notEnough": "⚠️ Pas assez d'emplacements.",
 "WKSH.tuning.sum.test": "<b>Test :</b> Mécanique {diff} — trouver la pièce : {price} cr ou test de Système D.",
 "WKSH.tuning.confirm.title": "Emplacements insuffisants",
 "WKSH.tuning.confirm.body": "{name} coûte {hp} emplacement(s), {free} libre(s). Forcer ?",
 "WKSH.tuning.roll.install": "🔧 Installation : {att} sur {item} — Mécanique",
 "WKSH.tuning.fail.title": "🔧 Installation ratée — {att}",
 "WKSH.tuning.fail.body": "Le test de Mécanique échoue : l'accessoire n'est pas monté sur {item}.",
 "WKSH.tuning.fail.despair": "💀 Désastre : pièce perdue ou objet endommagé (MJ).",
 "WKSH.tuning.fail.hint": "Retente avec plus de temps ou de meilleurs outils.",
 "WKSH.tuning.fail.notify": "🔧 Installation ratée ({att}) — rien de posé.",
 "WKSH.tuning.card.title": "🔧 Réglage — {item}",
 "WKSH.tuning.card.installed": "Accessoire installé : <b>{att}</b>",
 "WKSH.tuning.card.meta": "Emplacements : {used}/{total} · Coût : {price} cr · Rareté {rarity}",
 "WKSH.tuning.res.success": "<b>✅ Test réussi</b> — {pips} {n} succès",
 "WKSH.tuning.res.adv": "→ réduis le temps ou pose un mod gratuit",
 "WKSH.tuning.res.tri": "mod gratuit",
 "WKSH.tuning.res.thr": "légère complication",
 "WKSH.tuning.res.des": "désastre",
 "WKSH.tuning.res.noRoll": "Noté sans test — à valider par un jet de Mécanique en jeu.",
 "WKSH.tuning.trace": "🔧 <b>{att}</b> installé (Emp.{hp}).",
 "WKSH.tuning.done.install": "{att} posé sur {item}. Pour la méca complète, glisse l'accessoire depuis le compendium.",
 "WKSH.tuning.warn.noAttach": "{name} n'a aucun accessoire posé avec des mods activables. Pose d'abord un accessoire (ou glisse-le depuis le compendium sur l'objet).",
 "WKSH.tuning.opt.attMod": "{item} ▸ {att} — {active}/{total} mods activés",
 "WKSH.tuning.lbl.attInstalled": "Accessoire posé",
 "WKSH.tuning.lbl.mod": "Mod à activer",
 "WKSH.tuning.mod.title": "⚙️ Activer un mod d'accessoire",
 "WKSH.tuning.btn.modRoll": "Tenter la modif + test",
 "WKSH.tuning.btn.modNoRoll": "Activer sans test",
 "WKSH.tuning.mod.noneLeft": "— aucune option restante —",
 "WKSH.tuning.mod.fallbackName": "Mod",
 "WKSH.tuning.mod.fallbackAtt": "Accessoire",
 "WKSH.tuning.mod.count": "Mods activés sur cet accessoire : <b>{active}/{total}</b>",
 "WKSH.tuning.mod.exhausted": "plus d'option disponible",
 "WKSH.tuning.mod.testLine": "<b>Modification n° {n}</b> · <b>Test :</b> Mécanique {diff}",
 "WKSH.tuning.mod.hint": "Base Moyenne {pips}, +1 par mod déjà activé sur cet accessoire. Coût : trousse à outils + 100 cr.",
 "WKSH.tuning.mod.noneWarn": "Aucune option de mod restante sur cet accessoire.",
 "WKSH.tuning.roll.mod": "⚙️ Modification n°{n} : {mod} sur {att} — Mécanique {diff}",
 "WKSH.tuning.modFail.title": "⚙️ Modification ratée — {mod}",
 "WKSH.tuning.modFail.body": "Le test de Mécanique échoue : le mod n'est pas activé sur {att}.",
 "WKSH.tuning.modFail.despair": "💀 Désastre : accessoire endommagé, un mod déjà posé se désactive (MJ).",
 "WKSH.tuning.modFail.hint": "La difficulté ne monte pas (le mod n'est pas installé). Retente avec plus de temps / outils.",
 "WKSH.tuning.modFail.notify": "⚙️ Modification ratée ({mod}) sur {att}.",
 "WKSH.tuning.modCard.title": "⚙️ Modification — {item} ▸ {att}",
 "WKSH.tuning.modCard.activated": "Mod activé : <b>{mod}</b>",
 "WKSH.tuning.modCard.ok": "réussi",
 "WKSH.tuning.modCard.noRoll": "(sans test)",
 "WKSH.tuning.modCard.next": "Mods activés sur cet accessoire : <b>{now}/{total}</b> · prochaine modif = {diff}",
 "WKSH.tuning.modCard.adv": "→ temps réduit ou −1 diff. sur la prochaine",
 "WKSH.tuning.modCard.tri": "mod suivant gratuit",
 "WKSH.tuning.modCard.thr": "complication",
 "WKSH.tuning.modCard.des": "désastre",
 "WKSH.tuning.done.mod": "⚙️ {mod} activé sur {att} ({now}/{total}).",
 "WKSH.tuning.diff.0": "Simple",
 "WKSH.tuning.diff.1": "Facile",
 "WKSH.tuning.diff.2": "Moyenne",
 "WKSH.tuning.diff.3": "Difficile",
 "WKSH.tuning.diff.4": "Redoutable",
 "WKSH.tuning.diff.5": "Formidable",
 "WKSH.tuning.att.custGrip.n": "Poignée personnalisée",
 "WKSH.tuning.att.custGrip.note": "−1 {setback} aux tests de combat de l'utilisateur.",
 "WKSH.tuning.att.balStock.n": "Crosse équilibrée",
 "WKSH.tuning.att.balStock.note": "Qualité Verrouillage.",
 "WKSH.tuning.att.telescope.n": "Viseur télescopique",
 "WKSH.tuning.att.telescope.note": "Retire jusqu'à 2 {setback} dus à la portée (longue/extrême).",
 "WKSH.tuning.att.magazine.n": "Chargeur amélioré",
 "WKSH.tuning.att.bipod.n": "Bipied",
 "WKSH.tuning.att.bipod.note": "−1 difficulté {diff} si posé (manœuvre).",
 "WKSH.tuning.att.laserSight.n": "Mire laser",
 "WKSH.tuning.att.laserSight.note": "Ajoute {boost} aux tests d'attaque à courte portée.",
 "WKSH.tuning.att.cortosis.n": "Forge en cortosis",
 "WKSH.tuning.att.cortosis.note": "Qualité Cortosis.",
 "WKSH.tuning.att.plating.n": "Doublure de plaques",
 "WKSH.tuning.att.plating.note": "(armure) +1 Encaissement.",
 "WKSH.tuning.att.custom.n": "Autre / personnalisé",
 "WKSH.tuning.install.noParts": "Aucun accessoire compatible pour cet objet.",
 "WKSH.tuning.install.pick": "Coche au moins un accessoire.",
 "WKSH.tuning.sum.slotsUsed": "Emplacements :",
 "WKSH.tuning.sum.cost": "Coût : {price} cr · Rareté {rarity}",
 "WKSH.tuning.sum.testDyn": "<b>Test :</b> Mécanique {diff}",
 "WKSH.tuning.sum.weaponProfile": "Profil prévu — Dégâts <b>{dmg}</b> · Critique <b>{crit}</b>",
 "WKSH.tuning.sum.armorProfile": "Profil prévu — Encaissement <b>{soak}</b> · Défense <b>{def}</b>",
 "WKSH.tuning.card.weaponProfile": "Profil — Dégâts <b>{dmg}</b> · Critique <b>{crit}</b>",
 "WKSH.tuning.card.armorProfile": "Profil — Encaissement <b>{soak}</b> · Défense <b>{def}</b>"
}